animated_dice/__init__.py
animated_dice/dice_project.py
animated_dice/requirements.txt
animated_dice-0.1.0.dist-info/METADATA
animated_dice-0.1.0.dist-info/WHEEL
animated_dice-0.1.0.dist-info/RECORD
