Metadata-Version: 2.1
Name: animated-dice
Version: 0.1.0
Summary: animated dice
Author: logan maguire
Requires-Python: >=3.12.0,<4.0.0
Classifier: Programming Language :: Python :: 3
Classifier: Programming Language :: Python :: 3.12
Requires-Dist: requests (>=2.32.3,<3.0.0)
